{
    "configurations": [
        {
            "name": "Win32",
            "includePath": [
                "${workspaceFolder}/**",
                "C:/Qt/6.8.0/mingw_64/include",
                "C:/Qt/6.8.0/mingw_64/include/QtCore",
                "C:/Qt/6.8.0/mingw_64/include/QtGui",
                "C:/Qt/6.8.0/mingw_64/include/QtWidgets"
            ],
            "defines": [
                "_DEBUG",
                "UNICODE",
                "_UNICODE"
            ],
            "compilerPath": "C:\\MinGW\\bin\\gcc.exe",
            "cStandard": "c11",
            "cppStandard": "gnu++14",
            "intelliSenseMode": "windows-gcc-x86"
        }
    ],
    "version": 4
}